dbtmetabase/__init__.py
dbtmetabase/__main__.py
dbtmetabase/_exposures.py
dbtmetabase/_models.py
dbtmetabase/_version.py
dbtmetabase/core.py
dbtmetabase/errors.py
dbtmetabase/format.py
dbtmetabase/manifest.py
dbtmetabase/metabase.py
dbt_metabase-1.6.1.dist-info/LICENSE
dbt_metabase-1.6.1.dist-info/METADATA
dbt_metabase-1.6.1.dist-info/WHEEL
dbt_metabase-1.6.1.dist-info/entry_points.txt
dbt_metabase-1.6.1.dist-info/top_level.txt
dbt_metabase-1.6.1.dist-info/RECORD
