Metadata-Version: 2.1
Name: dbt-metabase
Version: 1.6.1
Summary: dbt + Metabase integration.
Author: Mike Gouline
License: MIT License
Project-URL: Homepage, https://github.com/gouline/dbt-metabase
Classifier: Intended Audience :: Developers
Classifier: License :: OSI Approved :: MIT License
Classifier: Operating System :: OS Independent
Classifier: Programming Language :: Python
Classifier: Programming Language :: Python :: 3 :: Only
Classifier: Programming Language :: Python :: 3.8
Classifier: Programming Language :: Python :: 3.9
Classifier: Programming Language :: Python :: 3.10
Classifier: Programming Language :: Python :: 3.11
Classifier: Programming Language :: Python :: 3.12
Classifier: Topic :: Software Development :: Libraries
Classifier: Topic :: Software Development :: Libraries :: Python Modules
Requires-Python: >=3.9
License-File: LICENSE
Requires-Dist: PyYAML >=5.4.1
Requires-Dist: requests >=2.26.0
Requires-Dist: click >=8.0.0
Requires-Dist: rich >=12.0.0
